[{"id":"5fe11165216ffa28e6bf28727b37c247","document_id":"d7139348a4aef6a6eeba8844f31a64d4","remote_id":"","file_name":"20230114_9.pdf","media_link":"https:\/\/api.docparser.com\/v1\/document\/media\/5mGGilPMpCitPQL8kmscTQJG3V9OHx7f2IEj6vsaIYVjqZFEg_WMaLB5QZV9xXNwiT9b5ihiB-RwDAoJBwprkbzKfZJbolca5OtbPHSdeco","media_link_original":"https:\/\/api.docparser.com\/v1\/document\/media\/5mGGilPMpCitPQL8kmscTQJG3V9OHx7f2IEj6vsaIYVjqZFEg_WMaLB5QZV9xXNwiT9b5ihiB-RwDAoJBwprkbzKfZJbolca5OtbPHSdeco\/original","media_link_data":"https:\/\/api.docparser.com\/v1\/document\/media\/5mGGilPMpCitPQL8kmscTQJG3V9OHx7f2IEj6vsaIYVjqZFEg_WMaLB5QZV9xXNwiT9b5ihiB-RwDAoJBwprkbzKfZJbolca5OtbPHSdeco\/data","page_count":3,"uploaded_at":"2023-01-14T15:30:39+00:00","processed_at":"2023-01-14T15:30:41+00:00","uploaded_at_utc":"2023-01-14T15:30:39+00:00","uploaded_at_user":"2023-01-14T07:30:39+00:00","processed_at_utc":"2023-01-14T15:30:41+00:00","processed_at_user":"2023-01-14T07:30:41+00:00","table_data":[{"key_0":"","key_1":"","key_2":"","key_3":"Injury R","key_4":"eport: 01\/14\/23","key_5":"09:30 AM","key_6":""},{"key_0":"Game Date","key_1":"Game Time","key_2":"Matchup","key_3":"Team","key_4":"Player Name","key_5":"Current Status","key_6":"Reason"},{"key_0":"01\/14\/2023","key_1":"01:00 (ET)","key_2":"MIL@MIA","key_3":"Miami Heat","key_4":"Haslem, Udonis","key_5":"Probable","key_6":"Injury\/Illness - Right Achilles; Tendinosis"},{"key_0":"","key_1":"","key_2":"","key_3":"","key_4":"Herro, Tyler","key_5":"Questionable","key_6":"Injury\/Illness - Left Achilles; Soreness"},{"key_0":"","key_1":"","key_2":"","key_3":"","key_4":"Jovic, Nikola","key_5":"Out","key_6":"Injury\/Illness - Lower Back; Stress Reaction"},{"key_0":"","key_1":"","key_2":"","key_3":"","key_4":"Lowry, Kyle","key_5":"Out","key_6":"Injury\/Illness - Left Knee; Discomfort"},{"key_0":"","key_1":"","key_2":"","key_3":"","key_4":"Martin, Caleb","key_5":"Probable","key_6":"Injury\/Illness - Left Quadriceps; Strain"},{"key_0":"","key_1":"","key_2":"","key_3":"","key_4":"Robinson, Duncan","key_5":"Out","key_6":"Injury\/Illness - Right 2nd Finger; Surgery"},{"key_0":"","key_1":"","key_2":"","key_3":"","key_4":"Yurtseven, Omer","key_5":"Out","key_6":"Injury\/Illness - Left Ankle; Surgery"},{"key_0":"","key_1":"","key_2":"","key_3":"Milwaukee Bucks","key_4":"Antetokounmpo, Giannis","key_5":"Questionable","key_6":"Injury\/Illness - Left Knee; Soreness"},{"key_0":"","key_1":"","key_2":"","key_3":"","key_4":"Ibaka, Serge","key_5":"Out","key_6":"Personal Reasons"},{"key_0":"","key_1":"","key_2":"","key_3":"","key_4":"Middleton, Khris","key_5":"Out","key_6":"Injury\/Illness - Right Knee; Soreness"},{"key_0":"","key_1":"07:00 (ET)","key_2":"BOS@CHA","key_3":"Boston Celtics","key_4":"Brogdon, Malcolm","key_5":"Questionable","key_6":"Personal Reasons"},{"key_0":"","key_1":"","key_2":"","key_3":"","key_4":"Brown, Jaylen","key_5":"Out","key_6":"Injury\/Illness - Right Adductor; Tightness"},{"key_0":"","key_1":"","key_2":"","key_3":"","key_4":"Davison, JD","key_5":"Out","key_6":"G League - Two-Way"},{"key_0":"","key_1":"","key_2":"","key_3":"","key_4":"Gallinari, Danilo","key_5":"Out","key_6":"Injury\/Illness - Left Knee; ACL Repair"},{"key_0":"","key_1":"","key_2":"","key_3":"","key_4":"Kabengele, Mfiondu","key_5":"Out","key_6":"G League - Two-Way"},{"key_0":"","key_1":"","key_2":"","key_3":"Charlotte Hornets","key_4":"Bouknight, James","key_5":"Out","key_6":"G League - On Assignment"},{"key_0":"","key_1":"","key_2":"","key_3":"","key_4":"Hayward, Gordon","key_5":"Doubtful","key_6":"Injury\/Illness - Left Hamstring; Soreness"},{"key_0":"","key_1":"","key_2":"","key_3":"","key_4":"Oubre Jr., Kelly","key_5":"Out","key_6":"Injury\/Illness - Left Hand; Surgery"},{"key_0":"","key_1":"","key_2":"MEM@IND","key_3":"Indiana Pacers","key_4":"","key_5":"","key_6":"NOT YET SUBMITTED"},{"key_0":"","key_1":"","key_2":"","key_3":"Memphis Grizzlies","key_4":"Brooks, Dillon","key_5":"Questionable","key_6":"Injury\/Illness - Right Ankle; Soreness"},{"key_0":"","key_1":"","key_2":"","key_3":"","key_4":"Chandler, Kennedy","key_5":"Available","key_6":"Injury\/Illness - Nasal; Fracture \/ Face Mask"},{"key_0":"","key_1":"","key_2":"","key_3":"","key_4":"Clarke, Brandon","key_5":"Questionable","key_6":"Injury\/Illness - Left Hip; Soreness"},{"key_0":"","key_1":"","key_2":"","key_3":"","key_4":"Green, Danny","key_5":"Out","key_6":"Injury\/Illness - Left Knee; Surgery Recovery"},{"key_0":"","key_1":"","key_2":"","key_3":"","key_4":"Konchar, John","key_5":"Out","key_6":"Injury\/Illness - Illness; Non-COVID Illness"},{"key_0":"","key_1":"","key_2":"","key_3":"","key_4":"Lofton Jr., Kenneth","key_5":"Out","key_6":"G League - Two-Way"},{"key_0":"","key_1":"07:30 (ET)","key_2":"ATL@TOR","key_3":"Atlanta Hawks","key_4":"","key_5":"","key_6":"NOT YET SUBMITTED"},{"key_0":"","key_1":"","key_2":"","key_3":"Toronto Raptors","key_4":"Banton, Dalano","key_5":"Out","key_6":"G League - On Assignment"},{"key_0":"","key_1":"","key_2":"","key_3":"","key_4":"Page 1 of 3","key_5":"","key_6":""},{"key_0":"","key_1":"","key_2":"","key_3":"Injury R","key_4":"eport: 01\/14\/23","key_5":"09:30 AM","key_6":""},{"key_0":"Game Date","key_1":"Game Time","key_2":"Matchup","key_3":"Team","key_4":"Player Name","key_5":"Current Status","key_6":"Reason"},{"key_0":"","key_1":"","key_2":"","key_3":"","key_4":"Dowtin Jr., Jeff","key_5":"Out","key_6":"G League - Two-Way"},{"key_0":"","key_1":"","key_2":"","key_3":"","key_4":"Harper Jr., Ron","key_5":"Out","key_6":"G League - Two-Way"},{"key_0":"","key_1":"","key_2":"","key_3":"","key_4":"Porter Jr., Otto","key_5":"Out","key_6":"Injury\/Illness - Left Foot; Surgery - second toe dislocation"},{"key_0":"","key_1":"08:00 (ET)","key_2":"CLE@MIN","key_3":"Cleveland Cavaliers","key_4":"Mobley, Isaiah","key_5":"Out","key_6":"G League - Two-Way"},{"key_0":"","key_1":"","key_2":"","key_3":"","key_4":"Wade, Dean","key_5":"Out","key_6":"Injury\/Illness - Left Shoulder; Sprain"},{"key_0":"","key_1":"","key_2":"","key_3":"","key_4":"Windler, Dylan","key_5":"Out","key_6":"Injury\/Illness - Right Ankle; Sprain"},{"key_0":"","key_1":"","key_2":"","key_3":"Minnesota Timberwolves","key_4":"","key_5":"","key_6":"NOT YET SUBMITTED"},{"key_0":"","key_1":"09:00 (ET)","key_2":"PHI@UTA","key_3":"Philadelphia 76ers","key_4":"Champagnie, Julian","key_5":"Out","key_6":"G League - Two-Way"},{"key_0":"","key_1":"","key_2":"","key_3":"","key_4":"Harris, Tobias","key_5":"Questionable","key_6":"Injury\/Illness - Left Knee; Soreness"},{"key_0":"","key_1":"","key_2":"","key_3":"","key_4":"King, Louis","key_5":"Out","key_6":"G League - Two-Way"},{"key_0":"","key_1":"","key_2":"","key_3":"Utah Jazz","key_4":"","key_5":"","key_6":"NOT YET SUBMITTED"},{"key_0":"","key_1":"10:00 (ET)","key_2":"DAL@POR","key_3":"Dallas Mavericks","key_4":"Finney-Smith, Dorian","key_5":"Out","key_6":"Injury\/Illness - Right Adductor; Strain"},{"key_0":"","key_1":"","key_2":"","key_3":"","key_4":"Green, Josh","key_5":"Out","key_6":"Injury\/Illness - Right Elbow; Sprain"},{"key_0":"","key_1":"","key_2":"","key_3":"","key_4":"Kleber, Maxi","key_5":"Out","key_6":"Injury\/Illness - Right Hamstring; Tear"},{"key_0":"","key_1":"","key_2":"","key_3":"","key_4":"Wood, Christian","key_5":"Questionable","key_6":"Injury\/Illness - Right Ankle; Sprain"},{"key_0":"","key_1":"","key_2":"","key_3":"Portland Trail Blazers","key_4":"Lillard, Damian","key_5":"Questionable","key_6":"Injury\/Illness - Left Ankle; Sprain"},{"key_0":"","key_1":"","key_2":"","key_3":"","key_4":"Little, Nassir","key_5":"Out","key_6":"Injury\/Illness - Right Femoral Head Impaction; Fracture"},{"key_0":"","key_1":"","key_2":"","key_3":"","key_4":"Payton II, Gary","key_5":"Probable","key_6":"Injury\/Illness - Right Ankle; Sprain"},{"key_0":"","key_1":"","key_2":"","key_3":"","key_4":"Winslow, Justise","key_5":"Out","key_6":"Injury\/Illness - Left Ankle; Sprain"},{"key_0":"01\/15\/2023","key_1":"01:00 (ET)","key_2":"NYK@DET","key_3":"Detroit Pistons","key_4":"","key_5":"","key_6":"NOT YET SUBMITTED"},{"key_0":"","key_1":"","key_2":"","key_3":"New York Knicks","key_4":"","key_5":"","key_6":"NOT YET SUBMITTED"},{"key_0":"","key_1":"03:00 (ET)","key_2":"HOU@LAC","key_3":"Houston Rockets","key_4":"","key_5":"","key_6":"NOT YET SUBMITTED"},{"key_0":"","key_1":"","key_2":"","key_3":"LA Clippers","key_4":"","key_5":"","key_6":"NOT YET SUBMITTED"},{"key_0":"","key_1":"03:30 (ET)","key_2":"GSW@CHI","key_3":"Chicago Bulls","key_4":"","key_5":"","key_6":"NOT YET SUBMITTED"},{"key_0":"","key_1":"","key_2":"","key_3":"Golden State Warriors","key_4":"","key_5":"","key_6":"NOT YET SUBMITTED"},{"key_0":"","key_1":"06:00 (ET)","key_2":"OKC@BKN","key_3":"Brooklyn Nets","key_4":"","key_5":"","key_6":"NOT YET SUBMITTED"},{"key_0":"","key_1":"","key_2":"","key_3":"Oklahoma City Thunder","key_4":"","key_5":"","key_6":"NOT YET SUBMITTED"},{"key_0":"","key_1":"","key_2":"","key_3":"","key_4":"Page 2 of 3","key_5":"","key_6":""},{"key_0":"","key_1":"","key_2":"","key_3":"Injury R","key_4":"eport: 01\/14\/23","key_5":"09:30 AM","key_6":""},{"key_0":"Game Date","key_1":"Game Time","key_2":"Matchup","key_3":"Team","key_4":"Player Name","key_5":"Current Status","key_6":"Reason"},{"key_0":"","key_1":"07:00 (ET)","key_2":"SAC@SAS","key_3":"Sacramento Kings","key_4":"","key_5":"","key_6":"NOT YET SUBMITTED"},{"key_0":"","key_1":"","key_2":"","key_3":"San Antonio Spurs","key_4":"","key_5":"","key_6":"NOT YET SUBMITTED"},{"key_0":"","key_1":"08:00 (ET)","key_2":"ORL@DEN","key_3":"Denver Nuggets","key_4":"","key_5":"","key_6":"NOT YET SUBMITTED"},{"key_0":"","key_1":"","key_2":"","key_3":"Orlando Magic","key_4":"Hampton, R.J.","key_5":"Out","key_6":"G League - On Assignment"},{"key_0":"","key_1":"","key_2":"","key_3":"","key_4":"Harris, Kevon","key_5":"Out","key_6":"G League - Two-Way"},{"key_0":"","key_1":"","key_2":"","key_3":"","key_4":"Isaac, Jonathan","key_5":"Out","key_6":"G League - On Assignment"},{"key_0":"","key_1":"","key_2":"","key_3":"","key_4":"Okeke, Chuma","key_5":"Out","key_6":"Injury\/Illness - Left Knee; Surgery"},{"key_0":"","key_1":"09:00 (ET)","key_2":"DAL@POR","key_3":"Dallas Mavericks","key_4":"","key_5":"","key_6":"NOT YET SUBMITTED"},{"key_0":"","key_1":"","key_2":"","key_3":"Portland Trail Blazers","key_4":"","key_5":"","key_6":"NOT YET SUBMITTED"},{"key_0":"","key_1":"09:30 (ET)","key_2":"PHI@LAL","key_3":"Los Angeles Lakers","key_4":"","key_5":"","key_6":"NOT YET SUBMITTED"},{"key_0":"","key_1":"","key_2":"","key_3":"Philadelphia 76ers","key_4":"","key_5":"","key_6":"NOT YET SUBMITTED"},{"key_0":"","key_1":"","key_2":"","key_3":"","key_4":"Page 3 of 3","key_5":"","key_6":""}]}]