[{"id":"e1c9fa8ba5d734e757a4233dddaf6a93","document_id":"3d53cb63e009f147343aac616249e3c9","remote_id":"","file_name":"20230428_15.pdf","media_link":"https:\/\/api.docparser.com\/v1\/document\/media\/JZXjCrsXndM5jeqveafKPEwdcVrxpvC02Ugpz6iz8LdjqZFEg_WMaLB5QZV9xXNwiT9b5ihiB-RwDAoJBwprkbzKfZJbolca5OtbPHSdeco","media_link_original":"https:\/\/api.docparser.com\/v1\/document\/media\/JZXjCrsXndM5jeqveafKPEwdcVrxpvC02Ugpz6iz8LdjqZFEg_WMaLB5QZV9xXNwiT9b5ihiB-RwDAoJBwprkbzKfZJbolca5OtbPHSdeco\/original","media_link_data":"https:\/\/api.docparser.com\/v1\/document\/media\/JZXjCrsXndM5jeqveafKPEwdcVrxpvC02Ugpz6iz8LdjqZFEg_WMaLB5QZV9xXNwiT9b5ihiB-RwDAoJBwprkbzKfZJbolca5OtbPHSdeco\/data","page_count":1,"uploaded_at":"2023-04-28T20:30:59+00:00","processed_at":"2023-04-28T20:31:01+00:00","uploaded_at_utc":"2023-04-28T20:30:59+00:00","uploaded_at_user":"2023-04-28T12:30:59+00:00","processed_at_utc":"2023-04-28T20:31:01+00:00","processed_at_user":"2023-04-28T12:31:01+00:00","table_data":[{"key_0":"","key_1":"","key_2":"","key_3":"Injury R","key_4":"eport: 04\/28\/2","key_5":"3 03:30 PM","key_6":""},{"key_0":"Game Date","key_1":"Game Time","key_2":"Matchup","key_3":"Team","key_4":"Player Name","key_5":"Current Status","key_6":"Reason"},{"key_0":"04\/28\/2023","key_1":"08:00 (ET)","key_2":"SAC@GSW","key_3":"Golden State Warriors","key_4":"Baldwin Jr., Patrick","key_5":"Doubtful","key_6":"Injury\/Illness - Left Toe; Soreness"},{"key_0":"","key_1":"","key_2":"","key_3":"","key_4":"Iguodala, Andre","key_5":"Out","key_6":"Injury\/Illness - Left Wrist; Surgery"},{"key_0":"","key_1":"","key_2":"","key_3":"","key_4":"Rollins, Ryan","key_5":"Out","key_6":"Injury\/Illness - Right Foot; Surgery"},{"key_0":"","key_1":"","key_2":"","key_3":"Sacramento Kings","key_4":"Dellavedova, Matthew","key_5":"Out","key_6":"Injury\/Illness - Right Index Finger; Surgery"},{"key_0":"","key_1":"10:30 (ET)","key_2":"MEM@LAL","key_3":"Los Angeles Lakers","key_4":"Davis, Anthony","key_5":"Probable","key_6":"Injury\/Illness - Right Foot; Stress injury"},{"key_0":"","key_1":"","key_2":"","key_3":"","key_4":"James, LeBron","key_5":"Probable","key_6":"Injury\/Illness - Right Foot; Soreness"},{"key_0":"","key_1":"","key_2":"","key_3":"","key_4":"Schroder, Dennis","key_5":"Probable","key_6":"Injury\/Illness - Right Achilles; Soreness"},{"key_0":"","key_1":"","key_2":"","key_3":"Memphis Grizzlies","key_4":"Adams, Steven","key_5":"Out","key_6":"Injury\/Illness - Right Knee; PCL Sprain"},{"key_0":"","key_1":"","key_2":"","key_3":"","key_4":"Clarke, Brandon","key_5":"Out","key_6":"Injury\/Illness - Left Achilles; Tear"},{"key_0":"","key_1":"","key_2":"","key_3":"","key_4":"Kennard, Luke","key_5":"Questionable","key_6":"Injury\/Illness - Left Shoulder; Soreness"},{"key_0":"","key_1":"","key_2":"","key_3":"","key_4":"LaRavia, Jake","key_5":"Out","key_6":"Injury\/Illness - Right Calf; Soreness"},{"key_0":"04\/29\/2023","key_1":"08:30 (ET)","key_2":"PHX@DEN","key_3":"Denver Nuggets","key_4":"","key_5":"","key_6":"NOT YET SUBMITTED"},{"key_0":"","key_1":"","key_2":"","key_3":"Phoenix Suns","key_4":"","key_5":"","key_6":"NOT YET SUBMITTED"},{"key_0":"","key_1":"","key_2":"","key_3":"","key_4":"Page 1 of 1","key_5":"","key_6":""}]}]