[{"id":"274b2a67b829afc063cbec42cc233ff1","document_id":"55891d5459fa84e3af03040f054d98e7","remote_id":"","file_name":"20240118_9.pdf","media_link":"https:\/\/api.docparser.com\/v1\/document\/media\/br41AGrk8G1UpORnx89fljC1DLgPeMDYOw9T7GsEtNZ9T1cwqssTJ3mHcT_Szaw-p5wUEPFc2JcQWMq3jipfDlWfW8rTN_YuT5djXhYealY","media_link_original":"https:\/\/api.docparser.com\/v1\/document\/media\/br41AGrk8G1UpORnx89fljC1DLgPeMDYOw9T7GsEtNZ9T1cwqssTJ3mHcT_Szaw-p5wUEPFc2JcQWMq3jipfDlWfW8rTN_YuT5djXhYealY\/original","media_link_data":"https:\/\/api.docparser.com\/v1\/document\/media\/br41AGrk8G1UpORnx89fljC1DLgPeMDYOw9T7GsEtNZ9T1cwqssTJ3mHcT_Szaw-p5wUEPFc2JcQWMq3jipfDlWfW8rTN_YuT5djXhYealY\/data","page_count":4,"uploaded_at":"2024-01-18T14:31:03+00:00","processed_at":"2024-01-18T14:31:05+00:00","uploaded_at_utc":"2024-01-18T14:31:03+00:00","uploaded_at_user":"2024-01-18T06:31:03+00:00","processed_at_utc":"2024-01-18T14:31:05+00:00","processed_at_user":"2024-01-18T06:31:05+00:00","table_data":[{"key_0":"","key_1":"","key_2":"","key_3":"Injury Repor","key_4":"t: 01\/18\/24 09:3","key_5":"0 AM","key_6":""},{"key_0":"Game Date","key_1":"Game Time","key_2":"Matchup","key_3":"Team","key_4":"Player Name","key_5":"Current Status","key_6":"Reason"},{"key_0":"01\/18\/2024","key_1":"07:30 (ET)","key_2":"CHI@TOR","key_3":"Chicago Bulls","key_4":"Ball, Lonzo","key_5":"Out","key_6":"Injury\/Illness - Left Knee; Surgery"},{"key_0":"","key_1":"","key_2":"","key_3":"","key_4":"Bitim, Onuralp","key_5":"Out","key_6":"G League - Two-Way"},{"key_0":"","key_1":"","key_2":"","key_3":"","key_4":"","key_5":"","key_6":"Injury\/Illness - Right Plantar Fascia;"},{"key_0":"","key_1":"","key_2":"","key_3":"","key_4":"Craig, Torrey","key_5":"Out","key_6":""},{"key_0":"","key_1":"","key_2":"","key_3":"","key_4":"","key_5":"","key_6":"Sprain"},{"key_0":"","key_1":"","key_2":"","key_3":"","key_4":"","key_5":"","key_6":"Injury\/Illness - Left Shoulder;"},{"key_0":"","key_1":"","key_2":"","key_3":"","key_4":"Dosunmu, Ayo","key_5":"Questionable","key_6":""},{"key_0":"","key_1":"","key_2":"","key_3":"","key_4":"","key_5":"","key_6":"Contusion"},{"key_0":"","key_1":"","key_2":"","key_3":"","key_4":"Drell, Henri","key_5":"Out","key_6":"G League - Two-Way"},{"key_0":"","key_1":"","key_2":"","key_3":"","key_4":"Drummond, Andre","key_5":"Probable","key_6":"Injury\/Illness - Right Low Back; Spasm"},{"key_0":"","key_1":"","key_2":"","key_3":"","key_4":"Phillips, Julian","key_5":"Out","key_6":"G League - On Assignment"},{"key_0":"","key_1":"","key_2":"","key_3":"","key_4":"Sanogo, Adama","key_5":"Out","key_6":"G League - Two-Way"},{"key_0":"","key_1":"","key_2":"","key_3":"","key_4":"","key_5":"","key_6":"Injury\/Illness - Left Patella Tendon;"},{"key_0":"","key_1":"","key_2":"","key_3":"","key_4":"Terry, Dalen","key_5":"Probable","key_6":""},{"key_0":"","key_1":"","key_2":"","key_3":"","key_4":"","key_5":"","key_6":"Tendonitis"},{"key_0":"","key_1":"","key_2":"","key_3":"","key_4":"Williams, Patrick","key_5":"Questionable","key_6":"Injury\/Illness - Right Ankle; Strain"},{"key_0":"","key_1":"","key_2":"","key_3":"Toronto Raptors","key_4":"","key_5":"","key_6":"NOT YET SUBMITTED"},{"key_0":"","key_1":"","key_2":"WAS@NYK","key_3":"Washington Wizards","key_4":"Gafford, Daniel","key_5":"Out","key_6":"Injury\/Illness - Head; Concussion"},{"key_0":"","key_1":"","key_2":"","key_3":"New York Knicks","key_4":"","key_5":"","key_6":"NOT YET SUBMITTED"},{"key_0":"","key_1":"09:00 (ET)","key_2":"OKC@UTA","key_3":"Utah Jazz","key_4":"Hendricks, Taylor","key_5":"Out","key_6":"G League - On Assignment"},{"key_0":"","key_1":"","key_2":"","key_3":"","key_4":"Juzang, Johnny","key_5":"Out","key_6":"G League - Two-Way"},{"key_0":"","key_1":"","key_2":"","key_3":"","key_4":"Potter, Micah","key_5":"Out","key_6":"G League - Two-Way"},{"key_0":"","key_1":"","key_2":"","key_3":"Pag","key_4":"e 1 of 4","key_5":"","key_6":""},{"key_0":"","key_1":"","key_2":"","key_3":"Injury Repor","key_4":"t: 01\/18\/24 09:3","key_5":"0 AM","key_6":""},{"key_0":"","key_1":"","key_2":"","key_3":"","key_4":"Preston, Jason","key_5":"Out","key_6":"G League - Two-Way"},{"key_0":"","key_1":"","key_2":"","key_3":"","key_4":"Sensabaugh, Brice","key_5":"Out","key_6":"G League - On Assignment"},{"key_0":"","key_1":"10:00 (ET)","key_2":"IND@SAC","key_3":"Indiana Pacers","key_4":"Brown, Bruce","key_5":"Out","key_6":"Trade Pending"},{"key_0":"","key_1":"","key_2":"","key_3":"","key_4":"Brown, Kendall","key_5":"Questionable","key_6":"G League - Two-Way"},{"key_0":"","key_1":"","key_2":"","key_3":"","key_4":"Haliburton, Tyrese","key_5":"Questionable","key_6":"Injury\/Illness - Left Hamstring; Strain"},{"key_0":"","key_1":"","key_2":"","key_3":"","key_4":"Lewis Jr., Kira","key_5":"Out","key_6":"Trade Pending"},{"key_0":"","key_1":"","key_2":"","key_3":"","key_4":"Mathurin, Bennedict","key_5":"Questionable","key_6":"Injury\/Illness - Left Ankle; Sprain"},{"key_0":"","key_1":"","key_2":"","key_3":"","key_4":"","key_5":"","key_6":"Injury\/Illness - Left Tibialis Anterior;"},{"key_0":"","key_1":"","key_2":"","key_3":"","key_4":"Nesmith, Aaron","key_5":"Questionable","key_6":""},{"key_0":"","key_1":"","key_2":"","key_3":"","key_4":"","key_5":"","key_6":"Strain"},{"key_0":"","key_1":"","key_2":"","key_3":"","key_4":"Nwora, Jordan","key_5":"Out","key_6":"Trade Pending"},{"key_0":"","key_1":"","key_2":"","key_3":"","key_4":"Toppin, Obi","key_5":"Questionable","key_6":"Injury\/Illness - Left Calf; Strain"},{"key_0":"","key_1":"","key_2":"","key_3":"","key_4":"Tshiebwe, Oscar","key_5":"Questionable","key_6":"G League - Two-Way"},{"key_0":"","key_1":"","key_2":"","key_3":"","key_4":"Wong, Isaiah","key_5":"Questionable","key_6":"G League - Two-Way"},{"key_0":"","key_1":"","key_2":"","key_3":"","key_4":"","key_5":"","key_6":"Injury\/Illness - Right Knee; PCL"},{"key_0":"","key_1":"","key_2":"MEM@MIN","key_3":"Memphis Grizzlies","key_4":"Adams, Steven","key_5":"Out","key_6":""},{"key_0":"","key_1":"","key_2":"","key_3":"","key_4":"","key_5":"","key_6":"Surgery"},{"key_0":"","key_1":"","key_2":"","key_3":"","key_4":"Bane, Desmond","key_5":"Out","key_6":"Injury\/Illness - Left Ankle; Sprain"},{"key_0":"","key_1":"","key_2":"","key_3":"","key_4":"","key_5":"","key_6":"Injury\/Illness - Left Achilles; Tendon"},{"key_0":"","key_1":"","key_2":"","key_3":"","key_4":"Clarke, Brandon","key_5":"Out","key_6":""},{"key_0":"","key_1":"","key_2":"","key_3":"","key_4":"","key_5":"","key_6":"Repair"},{"key_0":"","key_1":"","key_2":"","key_3":"","key_4":"LaRavia, Jake","key_5":"Out","key_6":"Injury\/Illness - Left Ankle; Sprain"},{"key_0":"","key_1":"","key_2":"","key_3":"","key_4":"","key_5":"","key_6":"Injury\/Illness - Right Shoulder; Labral"},{"key_0":"","key_1":"","key_2":"","key_3":"","key_4":"Morant, Ja","key_5":"Out","key_6":""},{"key_0":"","key_1":"","key_2":"","key_3":"","key_4":"","key_5":"","key_6":"Repair"},{"key_0":"","key_1":"","key_2":"","key_3":"Pag","key_4":"e 2 of 4","key_5":"","key_6":""},{"key_0":"","key_1":"","key_2":"","key_3":"Injury Repor","key_4":"t: 01\/18\/24 09:3","key_5":"0 AM","key_6":""},{"key_0":"","key_1":"","key_2":"","key_3":"","key_4":"Rose, Derrick","key_5":"Out","key_6":"Injury\/Illness - Left Hamstring; Strain"},{"key_0":"","key_1":"","key_2":"","key_3":"","key_4":"","key_5":"","key_6":"Injury\/Illness - Right Ring Finger;"},{"key_0":"","key_1":"","key_2":"","key_3":"","key_4":"Smart, Marcus","key_5":"Out","key_6":""},{"key_0":"","key_1":"","key_2":"","key_3":"","key_4":"","key_5":"","key_6":"Central Slip Tear"},{"key_0":"","key_1":"","key_2":"","key_3":"Minnesota Timberwolves","key_4":"","key_5":"","key_6":"NOT YET SUBMITTED"},{"key_0":"01\/19\/2024","key_1":"07:00 (ET)","key_2":"PHI@ORL","key_3":"Philadelphia 76ers","key_4":"","key_5":"","key_6":"NOT YET SUBMITTED"},{"key_0":"","key_1":"","key_2":"","key_3":"Orlando Magic","key_4":"","key_5":"","key_6":"NOT YET SUBMITTED"},{"key_0":"","key_1":"","key_2":"SAS@CHA","key_3":"San Antonio Spurs","key_4":"","key_5":"","key_6":"NOT YET SUBMITTED"},{"key_0":"","key_1":"","key_2":"","key_3":"Charlotte Hornets","key_4":"","key_5":"","key_6":"NOT YET SUBMITTED"},{"key_0":"","key_1":"07:30 (ET)","key_2":"DEN@BOS","key_3":"Denver Nuggets","key_4":"","key_5":"","key_6":"NOT YET SUBMITTED"},{"key_0":"","key_1":"","key_2":"","key_3":"Boston Celtics","key_4":"","key_5":"","key_6":"NOT YET SUBMITTED"},{"key_0":"","key_1":"08:00 (ET)","key_2":"ATL@MIA","key_3":"Atlanta Hawks","key_4":"","key_5":"","key_6":"NOT YET SUBMITTED"},{"key_0":"","key_1":"","key_2":"","key_3":"Miami Heat","key_4":"","key_5":"","key_6":"NOT YET SUBMITTED"},{"key_0":"","key_1":"","key_2":"PHX@NOP","key_3":"Phoenix Suns","key_4":"","key_5":"","key_6":"NOT YET SUBMITTED"},{"key_0":"","key_1":"","key_2":"","key_3":"New Orleans Pelicans","key_4":"","key_5":"","key_6":"NOT YET SUBMITTED"},{"key_0":"","key_1":"10:00 (ET)","key_2":"DAL@GSW","key_3":"Dallas Mavericks","key_4":"","key_5":"","key_6":"NOT YET SUBMITTED"},{"key_0":"","key_1":"","key_2":"","key_3":"Golden State Warriors","key_4":"","key_5":"","key_6":"NOT YET SUBMITTED"},{"key_0":"","key_1":"","key_2":"IND@POR","key_3":"Indiana Pacers","key_4":"","key_5":"","key_6":"NOT YET SUBMITTED"},{"key_0":"","key_1":"","key_2":"","key_3":"Portland Trail Blazers","key_4":"","key_5":"","key_6":"NOT YET SUBMITTED"},{"key_0":"","key_1":"10:30 (ET)","key_2":"BKN@LAL","key_3":"Brooklyn Nets","key_4":"","key_5":"","key_6":"NOT YET SUBMITTED"},{"key_0":"","key_1":"","key_2":"","key_3":"Pag","key_4":"e 3 of 4","key_5":"","key_6":""},{"key_0":"","key_1":"","key_2":"","key_3":"Injury Repor","key_4":"t: 01\/18\/24 09:3","key_5":"0 AM","key_6":""},{"key_0":"","key_1":"","key_2":"","key_3":"Los Angeles Lakers","key_4":"","key_5":"","key_6":"NOT YET SUBMITTED"},{"key_0":"","key_1":"","key_2":"","key_3":"Pag","key_4":"e 4 of 4","key_5":"","key_6":""}]}]